{
  "header": {
    "tfbh": "200503",
    "name": "桑卡",
    "ename": "Sonca",
    "start_time": "2005-04-23T08:00:00",
    "is_current": "0.0"
  },
  "points": [
    {
      "time": "2005-04-23T08:00:00",
      "lng": 132.810078,
      "lat": 11.604377,
      "pressure": 996.0,
      "speed": 18.0,
      "strong": "热带风暴(TS)",
      "power": 8.0,
      "move_dir": null,
      "move_speed": null
    },
    {
      "time": "2005-04-23T14:00:00",
      "lng": 131.910257,
      "lat": 12.204435,
      "pressure": 990.0,
      "speed": 23.0,
      "strong": "热带风暴(TS)",
      "power": 9.0,
      "move_dir": null,
      "move_speed": null
    },
    {
      "time": "2005-04-24T02:00:00",
      "lng": 131.310727,
      "lat": 13.304819,
      "pressure": 975.0,
      "speed": 30.0,
      "strong": "强热带风暴(STS)",
      "power": 11.0,
      "move_dir": null,
      "move_speed": null
    },
    {
      "time": "2005-04-24T08:00:00",
      "lng": 130.810504,
      "lat": 13.504992,
      "pressure": 975.0,
      "speed": 33.0,
      "strong": "台风(TY)",
      "power": 12.0,
      "move_dir": null,
      "move_speed": null
    },
    {
      "time": "2005-04-24T14:00:00",
      "lng": 130.710514,
      "lat": 14.004506,
      "pressure": 960.0,
      "speed": 40.0,
      "strong": "台风(TY)",
      "power": 13.0,
      "move_dir": null,
      "move_speed": null
    },
    {
      "time": "2005-04-24T20:00:00",
      "lng": 130.810552,
      "lat": 14.40457,
      "pressure": 950.0,
      "speed": 45.0,
      "strong": "强台风(STY)",
      "power": 14.0,
      "move_dir": null,
      "move_speed": null
    },
    {
      "time": "2005-04-25T02:00:00",
      "lng": 131.010779,
      "lat": 15.304197,
      "pressure": 950.0,
      "speed": 45.0,
      "strong": "强台风(STY)",
      "power": 14.0,
      "move_dir": null,
      "move_speed": null
    },
    {
      "time": "2005-04-25T14:00:00",
      "lng": 131.510874,
      "lat": 16.504444,
      "pressure": 950.0,
      "speed": 45.0,
      "strong": "强台风(STY)",
      "power": 14.0,
      "move_dir": null,
      "move_speed": null
    },
    {
      "time": "2005-04-25T20:00:00",
      "lng": 132.210687,
      "lat": 17.304457,
      "pressure": 950.0,
      "speed": 45.0,
      "strong": "强台风(STY)",
      "power": 14.0,
      "move_dir": null,
      "move_speed": null
    },
    {
      "time": "2005-04-26T02:00:00",
      "lng": 132.710431,
      "lat": 18.204643,
      "pressure": 955.0,
      "speed": 45.0,
      "strong": "强台风(STY)",
      "power": 14.0,
      "move_dir": null,
      "move_speed": null
    },
    {
      "time": "2005-04-26T08:00:00",
      "lng": 134.010654,
      "lat": 20.003868,
      "pressure": 955.0,
      "speed": 45.0,
      "strong": "强台风(STY)",
      "power": 14.0,
      "move_dir": null,
      "move_speed": null
    },
    {
      "time": "2005-04-26T14:00:00",
      "lng": 135.910832,
      "lat": 21.60299,
      "pressure": 965.0,
      "speed": 40.0,
      "strong": "台风(TY)",
      "power": 13.0,
      "move_dir": null,
      "move_speed": null
    },
    {
      "time": "2005-04-26T20:00:00",
      "lng": 138.110367,
      "lat": 23.404054,
      "pressure": 965.0,
      "speed": 40.0,
      "strong": "台风(TY)",
      "power": 13.0,
      "move_dir": null,
      "move_speed": null
    },
    {
      "time": "2005-04-27T02:00:00",
      "lng": 140.209476,
      "lat": 24.803142,
      "pressure": 965.0,
      "speed": 40.0,
      "strong": "台风(TY)",
      "power": 13.0,
      "move_dir": null,
      "move_speed": null
    },
    {
      "time": "2005-04-27T08:00:00",
      "lng": 142.808892,
      "lat": 25.503794,
      "pressure": 980.0,
      "speed": 30.0,
      "strong": "强热带风暴(STS)",
      "power": 11.0,
      "move_dir": null,
      "move_speed": null
    },
    {
      "time": "2005-04-27T14:00:00",
      "lng": 145.708098,
      "lat": 26.703058,
      "pressure": 985.0,
      "speed": 25.0,
      "strong": "强热带风暴(STS)",
      "power": 10.0,
      "move_dir": null,
      "move_speed": null
    }
  ]
}