{
  "header": {
    "tfbh": "201202",
    "name": "珊瑚",
    "ename": "Sanvu",
    "start_time": "2012-05-22T08:00:00",
    "is_current": "0"
  },
  "points": [
    {
      "time": "2012-05-22T08:00:00",
      "lng": 144.107805,
      "lat": 13.505064,
      "pressure": 1000,
      "speed": 18,
      "strong": "热带风暴(TS)",
      "power": 8,
      "move_dir": "西西北",
      "move_speed": 17.0
    },
    {
      "time": "2012-05-22T14:00:00",
      "lng": 143.308192,
      "lat": 13.904703,
      "pressure": 1000,
      "speed": 18,
      "strong": "热带风暴(TS)",
      "power": 8,
      "move_dir": "西西北",
      "move_speed": 18.0
    },
    {
      "time": "2012-05-22T20:00:00",
      "lng": 142.50833,
      "lat": 14.503773,
      "pressure": 998,
      "speed": 20,
      "strong": "热带风暴(TS)",
      "power": 8,
      "move_dir": "北西",
      "move_speed": 15.0
    },
    {
      "time": "2012-05-23T02:00:00",
      "lng": 141.708706,
      "lat": 15.504547,
      "pressure": 992,
      "speed": 23,
      "strong": "热带风暴(TS)",
      "power": 9,
      "move_dir": "北北西",
      "move_speed": 20.0
    },
    {
      "time": "2012-05-23T08:00:00",
      "lng": 141.008738,
      "lat": 16.104634,
      "pressure": 996,
      "speed": 20,
      "strong": "热带风暴(TS)",
      "power": 8,
      "move_dir": "北北西",
      "move_speed": 15.0
    },
    {
      "time": "2012-05-23T14:00:00",
      "lng": 140.408898,
      "lat": 16.804894,
      "pressure": 992,
      "speed": 23,
      "strong": "热带风暴(TS)",
      "power": 9,
      "move_dir": "西北",
      "move_speed": 15.0
    },
    {
      "time": "2012-05-23T20:00:00",
      "lng": 139.809016,
      "lat": 17.204879,
      "pressure": 988,
      "speed": 25,
      "strong": "强热带风暴(STS)",
      "power": 10,
      "move_dir": "西北",
      "move_speed": 15.0
    },
    {
      "time": "2012-05-24T02:00:00",
      "lng": 139.709147,
      "lat": 17.904667,
      "pressure": 988,
      "speed": 25,
      "strong": "强热带风暴(STS)",
      "power": 10,
      "move_dir": "北西北",
      "move_speed": 15.0
    },
    {
      "time": "2012-05-24T08:00:00",
      "lng": 139.409622,
      "lat": 19.004427,
      "pressure": 988,
      "speed": 25,
      "strong": "强热带风暴(STS)",
      "power": 10,
      "move_dir": "北西北",
      "move_speed": 15.0
    },
    {
      "time": "2012-05-24T14:00:00",
      "lng": 139.209475,
      "lat": 19.704698,
      "pressure": 980,
      "speed": 30,
      "strong": "强热带风暴(STS)",
      "power": 11,
      "move_dir": "北西北",
      "move_speed": 13.0
    },
    {
      "time": "2012-05-24T20:00:00",
      "lng": 138.809534,
      "lat": 20.603455,
      "pressure": 975,
      "speed": 33,
      "strong": "台风(TY)",
      "power": 12,
      "move_dir": "北北东",
      "move_speed": 13.0
    },
    {
      "time": "2012-05-25T02:00:00",
      "lng": 139.009662,
      "lat": 21.603327,
      "pressure": 975,
      "speed": 33,
      "strong": "台风(TY)",
      "power": 12,
      "move_dir": "北北东",
      "move_speed": 13.0
    },
    {
      "time": "2012-05-25T08:00:00",
      "lng": 139.209623,
      "lat": 22.303779,
      "pressure": 970,
      "speed": 35,
      "strong": "台风(TY)",
      "power": 12,
      "move_dir": "北北东",
      "move_speed": 15.0
    },
    {
      "time": "2012-05-25T14:00:00",
      "lng": 139.509728,
      "lat": 23.103092,
      "pressure": 970,
      "speed": 35,
      "strong": "台风(TY)",
      "power": 12,
      "move_dir": "东北",
      "move_speed": 15.0
    },
    {
      "time": "2012-05-25T20:00:00",
      "lng": 140.009481,
      "lat": 23.803434,
      "pressure": 970,
      "speed": 35,
      "strong": "台风(TY)",
      "power": 12,
      "move_dir": "东北",
      "move_speed": 20.0
    },
    {
      "time": "2012-05-26T02:00:00",
      "lng": 140.509182,
      "lat": 24.103735,
      "pressure": 970,
      "speed": 35,
      "strong": "台风(TY)",
      "power": 12,
      "move_dir": "东北",
      "move_speed": 15.0
    },
    {
      "time": "2012-05-26T08:00:00",
      "lng": 141.309568,
      "lat": 24.602987,
      "pressure": 975,
      "speed": 33,
      "strong": "台风(TY)",
      "power": 12,
      "move_dir": "东北",
      "move_speed": 18.0
    },
    {
      "time": "2012-05-26T14:00:00",
      "lng": 142.009324,
      "lat": 24.903131,
      "pressure": 975,
      "speed": 33,
      "strong": "台风(TY)",
      "power": 12,
      "move_dir": "东北",
      "move_speed": 20.0
    },
    {
      "time": "2012-05-26T20:00:00",
      "lng": 143.508829,
      "lat": 25.303707,
      "pressure": 975,
      "speed": 33,
      "strong": "台风(TY)",
      "power": 12,
      "move_dir": "东北",
      "move_speed": 25.0
    },
    {
      "time": "2012-05-27T02:00:00",
      "lng": 144.008455,
      "lat": 25.903652,
      "pressure": 980,
      "speed": 30,
      "strong": "强热带风暴(STS)",
      "power": 11,
      "move_dir": "东北",
      "move_speed": 25.0
    }
  ]
}