{
  "header": {
    "tfbh": "201515",
    "name": "天鹅",
    "ename": "Goni",
    "start_time": "2015-08-15T02:00:00",
    "is_current": "0"
  },
  "points": [
    {
      "time": "2015-08-15T02:00:00",
      "lng": 148.207583,
      "lat": 12.905021,
      "pressure": 998,
      "speed": 18,
      "strong": "热带风暴(TS)",
      "power": 8,
      "move_dir": "西北",
      "move_speed": 12.0
    },
    {
      "time": "2015-08-15T08:00:00",
      "lng": 146.807216,
      "lat": 13.204345,
      "pressure": 995,
      "speed": 20,
      "strong": "热带风暴(TS)",
      "power": 8,
      "move_dir": "西北",
      "move_speed": 11.0
    },
    {
      "time": "2015-08-15T14:00:00",
      "lng": 146.307196,
      "lat": 14.104611,
      "pressure": 990,
      "speed": 23,
      "strong": "热带风暴(TS)",
      "power": 9,
      "move_dir": "西北",
      "move_speed": 10.0
    },
    {
      "time": "2015-08-15T17:00:00",
      "lng": 146.007283,
      "lat": 14.204106,
      "pressure": 990,
      "speed": 23,
      "strong": "热带风暴(TS)",
      "power": 9,
      "move_dir": null,
      "move_speed": 0.0
    },
    {
      "time": "2015-08-15T20:00:00",
      "lng": 145.707302,
      "lat": 14.304422,
      "pressure": 990,
      "speed": 23,
      "strong": "热带风暴(TS)",
      "power": 9,
      "move_dir": "西北",
      "move_speed": 11.0
    },
    {
      "time": "2015-08-16T02:00:00",
      "lng": 145.207408,
      "lat": 14.304742,
      "pressure": 990,
      "speed": 23,
      "strong": "热带风暴(TS)",
      "power": 9,
      "move_dir": "西北",
      "move_speed": 12.0
    },
    {
      "time": "2015-08-16T05:00:00",
      "lng": 144.907205,
      "lat": 14.503579,
      "pressure": 985,
      "speed": 25,
      "strong": "强热带风暴(STS)",
      "power": 10,
      "move_dir": null,
      "move_speed": 0.0
    },
    {
      "time": "2015-08-16T08:00:00",
      "lng": 144.707322,
      "lat": 14.704378,
      "pressure": 982,
      "speed": 28,
      "strong": "强热带风暴(STS)",
      "power": 10,
      "move_dir": "西西北",
      "move_speed": 16.0
    },
    {
      "time": "2015-08-16T14:00:00",
      "lng": 144.207698,
      "lat": 15.104121,
      "pressure": 982,
      "speed": 28,
      "strong": "强热带风暴(STS)",
      "power": 10,
      "move_dir": "西西北",
      "move_speed": 16.0
    },
    {
      "time": "2015-08-16T17:00:00",
      "lng": 143.708081,
      "lat": 15.303845,
      "pressure": 980,
      "speed": 30,
      "strong": "强热带风暴(STS)",
      "power": 11,
      "move_dir": null,
      "move_speed": 0.0
    },
    {
      "time": "2015-08-16T20:00:00",
      "lng": 143.408414,
      "lat": 15.504951,
      "pressure": 980,
      "speed": 30,
      "strong": "强热带风暴(STS)",
      "power": 11,
      "move_dir": "西西北",
      "move_speed": 22.0
    },
    {
      "time": "2015-08-17T02:00:00",
      "lng": 142.708309,
      "lat": 16.004376,
      "pressure": 975,
      "speed": 33,
      "strong": "台风(TY)",
      "power": 12,
      "move_dir": "西西北",
      "move_speed": 23.0
    },
    {
      "time": "2015-08-17T05:00:00",
      "lng": 142.308505,
      "lat": 16.204488,
      "pressure": 965,
      "speed": 38,
      "strong": "台风(TY)",
      "power": 13,
      "move_dir": null,
      "move_speed": 0.0
    },
    {
      "time": "2015-08-17T08:00:00",
      "lng": 141.708754,
      "lat": 16.5044,
      "pressure": 935,
      "speed": 52,
      "strong": "超强台风(Super TY)",
      "power": 16,
      "move_dir": "西西北",
      "move_speed": 25.0
    },
    {
      "time": "2015-08-17T11:00:00",
      "lng": 141.109005,
      "lat": 16.804736,
      "pressure": 935,
      "speed": 52,
      "strong": "超强台风(Super TY)",
      "power": 16,
      "move_dir": null,
      "move_speed": 0.0
    },
    {
      "time": "2015-08-17T14:00:00",
      "lng": 140.508704,
      "lat": 17.00465,
      "pressure": 935,
      "speed": 52,
      "strong": "超强台风(Super TY)",
      "power": 16,
      "move_dir": "西西北",
      "move_speed": 25.0
    },
    {
      "time": "2015-08-17T17:00:00",
      "lng": 139.908828,
      "lat": 17.204574,
      "pressure": 935,
      "speed": 52,
      "strong": "超强台风(Super TY)",
      "power": 16,
      "move_dir": null,
      "move_speed": 0.0
    },
    {
      "time": "2015-08-17T20:00:00",
      "lng": 139.209307,
      "lat": 17.405035,
      "pressure": 940,
      "speed": 50,
      "strong": "强台风(STY)",
      "power": 15,
      "move_dir": "西西北",
      "move_speed": 26.0
    },
    {
      "time": "2015-08-18T02:00:00",
      "lng": 137.710192,
      "lat": 17.804127,
      "pressure": 940,
      "speed": 50,
      "strong": "强台风(STY)",
      "power": 15,
      "move_dir": "西西北",
      "move_speed": 26.0
    },
    {
      "time": "2015-08-18T05:00:00",
      "lng": 136.910184,
      "lat": 18.004594,
      "pressure": 945,
      "speed": 48,
      "strong": "强台风(STY)",
      "power": 15,
      "move_dir": null,
      "move_speed": 0.0
    },
    {
      "time": "2015-08-18T08:00:00",
      "lng": 136.010687,
      "lat": 18.204155,
      "pressure": 945,
      "speed": 48,
      "strong": "强台风(STY)",
      "power": 15,
      "move_dir": "西",
      "move_speed": 28.0
    },
    {
      "time": "2015-08-18T14:00:00",
      "lng": 134.710523,
      "lat": 18.603904,
      "pressure": 945,
      "speed": 48,
      "strong": "强台风(STY)",
      "power": 15,
      "move_dir": "西",
      "move_speed": 26.0
    },
    {
      "time": "2015-08-18T17:00:00",
      "lng": 133.710575,
      "lat": 18.704414,
      "pressure": 945,
      "speed": 50,
      "strong": "强台风(STY)",
      "power": 15,
      "move_dir": null,
      "move_speed": 0.0
    },
    {
      "time": "2015-08-18T20:00:00",
      "lng": 132.910441,
      "lat": 18.803764,
      "pressure": 940,
      "speed": 50,
      "strong": "强台风(STY)",
      "power": 15,
      "move_dir": "西",
      "move_speed": 23.0
    },
    {
      "time": "2015-08-18T23:00:00",
      "lng": 132.010762,
      "lat": 18.804722,
      "pressure": 940,
      "speed": 50,
      "strong": "强台风(STY)",
      "power": 15,
      "move_dir": "西",
      "move_speed": 23.0
    },
    {
      "time": "2015-08-19T02:00:00",
      "lng": 131.111262,
      "lat": 18.804137,
      "pressure": 940,
      "speed": 50,
      "strong": "强台风(STY)",
      "power": 15,
      "move_dir": "西",
      "move_speed": 21.0
    },
    {
      "time": "2015-08-19T05:00:00",
      "lng": 130.41105,
      "lat": 18.804406,
      "pressure": 940,
      "speed": 50,
      "strong": "强台风(STY)",
      "power": 15,
      "move_dir": "西",
      "move_speed": 21.0
    },
    {
      "time": "2015-08-19T08:00:00",
      "lng": 129.810877,
      "lat": 18.804172,
      "pressure": 940,
      "speed": 50,
      "strong": "强台风(STY)",
      "power": 15,
      "move_dir": "西",
      "move_speed": 19.0
    },
    {
      "time": "2015-08-19T11:00:00",
      "lng": 129.010516,
      "lat": 18.904716,
      "pressure": 940,
      "speed": 50,
      "strong": "强台风(STY)",
      "power": 15,
      "move_dir": "西",
      "move_speed": 18.0
    },
    {
      "time": "2015-08-19T14:00:00",
      "lng": 128.510239,
      "lat": 19.004603,
      "pressure": 940,
      "speed": 50,
      "strong": "强台风(STY)",
      "power": 15,
      "move_dir": "西",
      "move_speed": 17.0
    },
    {
      "time": "2015-08-19T17:00:00",
      "lng": 127.710216,
      "lat": 19.004425,
      "pressure": 940,
      "speed": 50,
      "strong": "强台风(STY)",
      "power": 15,
      "move_dir": "西",
      "move_speed": 15.0
    },
    {
      "time": "2015-08-19T20:00:00",
      "lng": 127.310216,
      "lat": 18.904627,
      "pressure": 930,
      "speed": 55,
      "strong": "超强台风(Super TY)",
      "power": 16,
      "move_dir": "西",
      "move_speed": 14.0
    },
    {
      "time": "2015-08-19T23:00:00",
      "lng": 126.709927,
      "lat": 18.904531,
      "pressure": 930,
      "speed": 55,
      "strong": "超强台风(Super TY)",
      "power": 16,
      "move_dir": "西",
      "move_speed": 13.0
    },
    {
      "time": "2015-08-20T02:00:00",
      "lng": 126.210166,
      "lat": 18.904247,
      "pressure": 930,
      "speed": 55,
      "strong": "超强台风(Super TY)",
      "power": 16,
      "move_dir": "西",
      "move_speed": 12.0
    },
    {
      "time": "2015-08-20T05:00:00",
      "lng": 125.510382,
      "lat": 18.904575,
      "pressure": 930,
      "speed": 55,
      "strong": "超强台风(Super TY)",
      "power": 16,
      "move_dir": "西西北",
      "move_speed": 9.0
    },
    {
      "time": "2015-08-20T08:00:00",
      "lng": 125.310453,
      "lat": 18.904484,
      "pressure": 930,
      "speed": 55,
      "strong": "超强台风(Super TY)",
      "power": 16,
      "move_dir": "西西北",
      "move_speed": 8.0
    },
    {
      "time": "2015-08-20T11:00:00",
      "lng": 125.010371,
      "lat": 18.904204,
      "pressure": 935,
      "speed": 52,
      "strong": "超强台风(Super TY)",
      "power": 16,
      "move_dir": "西西北",
      "move_speed": 8.0
    },
    {
      "time": "2015-08-20T14:00:00",
      "lng": 124.61011,
      "lat": 19.003905,
      "pressure": 935,
      "speed": 52,
      "strong": "超强台风(Super TY)",
      "power": 16,
      "move_dir": "西西北",
      "move_speed": 8.0
    },
    {
      "time": "2015-08-20T17:00:00",
      "lng": 124.31028,
      "lat": 19.004623,
      "pressure": 935,
      "speed": 52,
      "strong": "超强台风(Super TY)",
      "power": 16,
      "move_dir": "西西北",
      "move_speed": 7.0
    },
    {
      "time": "2015-08-20T20:00:00",
      "lng": 124.110495,
      "lat": 19.104639,
      "pressure": 935,
      "speed": 52,
      "strong": "超强台风(Super TY)",
      "power": 16,
      "move_dir": "西北",
      "move_speed": 7.0
    },
    {
      "time": "2015-08-20T23:00:00",
      "lng": 123.710298,
      "lat": 19.204538,
      "pressure": 940,
      "speed": 50,
      "strong": "强台风(STY)",
      "power": 15,
      "move_dir": "西北",
      "move_speed": 6.0
    },
    {
      "time": "2015-08-21T02:00:00",
      "lng": 123.210307,
      "lat": 19.204259,
      "pressure": 945,
      "speed": 48,
      "strong": "强台风(STY)",
      "power": 15,
      "move_dir": "北西北",
      "move_speed": 6.0
    },
    {
      "time": "2015-08-21T05:00:00",
      "lng": 123.010064,
      "lat": 19.204695,
      "pressure": 945,
      "speed": 48,
      "strong": "强台风(STY)",
      "power": 15,
      "move_dir": "北西北",
      "move_speed": 6.0
    },
    {
      "time": "2015-08-21T08:00:00",
      "lng": 122.809992,
      "lat": 19.204049,
      "pressure": 945,
      "speed": 48,
      "strong": "强台风(STY)",
      "power": 15,
      "move_dir": "北西北",
      "move_speed": 6.0
    },
    {
      "time": "2015-08-21T11:00:00",
      "lng": 122.509849,
      "lat": 19.404538,
      "pressure": 945,
      "speed": 48,
      "strong": "强台风(STY)",
      "power": 15,
      "move_dir": "北",
      "move_speed": 7.0
    },
    {
      "time": "2015-08-21T14:00:00",
      "lng": 122.410038,
      "lat": 19.504816,
      "pressure": 945,
      "speed": 48,
      "strong": "强台风(STY)",
      "power": 15,
      "move_dir": "北",
      "move_speed": 8.0
    },
    {
      "time": "2015-08-21T17:00:00",
      "lng": 122.309899,
      "lat": 19.304487,
      "pressure": 945,
      "speed": 48,
      "strong": "强台风(STY)",
      "power": 15,
      "move_dir": "北",
      "move_speed": 8.0
    },
    {
      "time": "2015-08-21T20:00:00",
      "lng": 122.410014,
      "lat": 19.404846,
      "pressure": 945,
      "speed": 48,
      "strong": "强台风(STY)",
      "power": 15,
      "move_dir": "北东北",
      "move_speed": 12.0
    },
    {
      "time": "2015-08-21T23:00:00",
      "lng": 122.509872,
      "lat": 19.504508,
      "pressure": 945,
      "speed": 48,
      "strong": "强台风(STY)",
      "power": 15,
      "move_dir": "北",
      "move_speed": 13.0
    },
    {
      "time": "2015-08-22T02:00:00",
      "lng": 122.509898,
      "lat": 19.704405,
      "pressure": 950,
      "speed": 45,
      "strong": "强台风(STY)",
      "power": 14,
      "move_dir": "北",
      "move_speed": 16.0
    },
    {
      "time": "2015-08-22T03:00:00",
      "lng": 122.509885,
      "lat": 19.804333,
      "pressure": 950,
      "speed": 45,
      "strong": "强台风(STY)",
      "power": 14,
      "move_dir": "北东北",
      "move_speed": 15.0
    },
    {
      "time": "2015-08-22T04:00:00",
      "lng": 122.509885,
      "lat": 19.804333,
      "pressure": 950,
      "speed": 45,
      "strong": "强台风(STY)",
      "power": 14,
      "move_dir": "北东北",
      "move_speed": 15.0
    },
    {
      "time": "2015-08-22T05:00:00",
      "lng": 122.509885,
      "lat": 19.804333,
      "pressure": 950,
      "speed": 45,
      "strong": "强台风(STY)",
      "power": 14,
      "move_dir": "北东北",
      "move_speed": 15.0
    },
    {
      "time": "2015-08-22T06:00:00",
      "lng": 122.60977,
      "lat": 20.003623,
      "pressure": 950,
      "speed": 45,
      "strong": "强台风(STY)",
      "power": 14,
      "move_dir": "北东北",
      "move_speed": 15.0
    },
    {
      "time": "2015-08-22T07:00:00",
      "lng": 122.609794,
      "lat": 20.103545,
      "pressure": 950,
      "speed": 45,
      "strong": "强台风(STY)",
      "power": 14,
      "move_dir": "北东北",
      "move_speed": 15.0
    },
    {
      "time": "2015-08-22T08:00:00",
      "lng": 122.609794,
      "lat": 20.103545,
      "pressure": 950,
      "speed": 45,
      "strong": "强台风(STY)",
      "power": 14,
      "move_dir": "北东北",
      "move_speed": 16.0
    },
    {
      "time": "2015-08-22T09:00:00",
      "lng": 122.609816,
      "lat": 20.20347,
      "pressure": 950,
      "speed": 45,
      "strong": "强台风(STY)",
      "power": 14,
      "move_dir": "北东北",
      "move_speed": 16.0
    },
    {
      "time": "2015-08-22T10:00:00",
      "lng": 122.609819,
      "lat": 20.303399,
      "pressure": 950,
      "speed": 45,
      "strong": "强台风(STY)",
      "power": 14,
      "move_dir": "北东北",
      "move_speed": 15.0
    },
    {
      "time": "2015-08-22T11:00:00",
      "lng": 122.609819,
      "lat": 20.303399,
      "pressure": 950,
      "speed": 45,
      "strong": "强台风(STY)",
      "power": 14,
      "move_dir": "北东北",
      "move_speed": 16.0
    },
    {
      "time": "2015-08-22T12:00:00",
      "lng": 122.710034,
      "lat": 20.403243,
      "pressure": 950,
      "speed": 45,
      "strong": "强台风(STY)",
      "power": 14,
      "move_dir": "北东北",
      "move_speed": 16.0
    },
    {
      "time": "2015-08-22T13:00:00",
      "lng": 122.710025,
      "lat": 20.503192,
      "pressure": 950,
      "speed": 45,
      "strong": "强台风(STY)",
      "power": 14,
      "move_dir": "北东北",
      "move_speed": 15.0
    },
    {
      "time": "2015-08-22T14:00:00",
      "lng": 122.810087,
      "lat": 20.70326,
      "pressure": 950,
      "speed": 45,
      "strong": "强台风(STY)",
      "power": 14,
      "move_dir": "北东北",
      "move_speed": 16.0
    },
    {
      "time": "2015-08-22T15:00:00",
      "lng": 122.810109,
      "lat": 20.803251,
      "pressure": 950,
      "speed": 45,
      "strong": "强台风(STY)",
      "power": 14,
      "move_dir": "北东北",
      "move_speed": 16.0
    },
    {
      "time": "2015-08-22T16:00:00",
      "lng": 122.909958,
      "lat": 20.903471,
      "pressure": 950,
      "speed": 45,
      "strong": "强台风(STY)",
      "power": 14,
      "move_dir": "北东北",
      "move_speed": 16.0
    },
    {
      "time": "2015-08-22T17:00:00",
      "lng": 122.909946,
      "lat": 21.003471,
      "pressure": 950,
      "speed": 45,
      "strong": "强台风(STY)",
      "power": 14,
      "move_dir": "北东北",
      "move_speed": 16.0
    },
    {
      "time": "2015-08-22T18:00:00",
      "lng": 123.010156,
      "lat": 21.103898,
      "pressure": 950,
      "speed": 45,
      "strong": "强台风(STY)",
      "power": 14,
      "move_dir": "北东北",
      "move_speed": 16.0
    },
    {
      "time": "2015-08-22T19:00:00",
      "lng": 123.010164,
      "lat": 21.203902,
      "pressure": 950,
      "speed": 45,
      "strong": "强台风(STY)",
      "power": 14,
      "move_dir": "北东北",
      "move_speed": 16.0
    },
    {
      "time": "2015-08-22T20:00:00",
      "lng": 123.11047,
      "lat": 21.303976,
      "pressure": 950,
      "speed": 45,
      "strong": "强台风(STY)",
      "power": 14,
      "move_dir": "北东北",
      "move_speed": 18.0
    },
    {
      "time": "2015-08-22T21:00:00",
      "lng": 123.210464,
      "lat": 21.403467,
      "pressure": 950,
      "speed": 45,
      "strong": "强台风(STY)",
      "power": 14,
      "move_dir": "北东北",
      "move_speed": 18.0
    },
    {
      "time": "2015-08-22T22:00:00",
      "lng": 123.210456,
      "lat": 21.603423,
      "pressure": 950,
      "speed": 45,
      "strong": "强台风(STY)",
      "power": 14,
      "move_dir": "北东北",
      "move_speed": 18.0
    },
    {
      "time": "2015-08-22T23:00:00",
      "lng": 123.310552,
      "lat": 21.8031,
      "pressure": 955,
      "speed": 42,
      "strong": "强台风(STY)",
      "power": 14,
      "move_dir": "北东北",
      "move_speed": 18.0
    },
    {
      "time": "2015-08-23T00:00:00",
      "lng": 123.310577,
      "lat": 21.903058,
      "pressure": 955,
      "speed": 42,
      "strong": "强台风(STY)",
      "power": 14,
      "move_dir": "北东北",
      "move_speed": 18.0
    },
    {
      "time": "2015-08-23T01:00:00",
      "lng": 123.310599,
      "lat": 22.003015,
      "pressure": 955,
      "speed": 42,
      "strong": "强台风(STY)",
      "power": 14,
      "move_dir": "北东北",
      "move_speed": 18.0
    },
    {
      "time": "2015-08-23T02:00:00",
      "lng": 123.310584,
      "lat": 22.302897,
      "pressure": 955,
      "speed": 42,
      "strong": "强台风(STY)",
      "power": 14,
      "move_dir": "北东北",
      "move_speed": 19.0
    },
    {
      "time": "2015-08-23T03:00:00",
      "lng": 123.310593,
      "lat": 22.40288,
      "pressure": 955,
      "speed": 42,
      "strong": "强台风(STY)",
      "power": 14,
      "move_dir": "北东北",
      "move_speed": 19.0
    },
    {
      "time": "2015-08-23T04:00:00",
      "lng": 123.310618,
      "lat": 22.502879,
      "pressure": 955,
      "speed": 42,
      "strong": "强台风(STY)",
      "power": 14,
      "move_dir": "北东北",
      "move_speed": 19.0
    },
    {
      "time": "2015-08-23T05:00:00",
      "lng": 123.41082,
      "lat": 22.703163,
      "pressure": 960,
      "speed": 40,
      "strong": "台风(TY)",
      "power": 13,
      "move_dir": "北东北",
      "move_speed": 18.0
    },
    {
      "time": "2015-08-23T06:00:00",
      "lng": 123.410809,
      "lat": 22.803191,
      "pressure": 960,
      "speed": 40,
      "strong": "台风(TY)",
      "power": 13,
      "move_dir": "北东北",
      "move_speed": 18.0
    },
    {
      "time": "2015-08-23T07:00:00",
      "lng": 123.4108,
      "lat": 22.903228,
      "pressure": 960,
      "speed": 40,
      "strong": "台风(TY)",
      "power": 13,
      "move_dir": "北东北",
      "move_speed": 18.0
    },
    {
      "time": "2015-08-23T08:00:00",
      "lng": 123.410835,
      "lat": 23.103318,
      "pressure": 965,
      "speed": 38,
      "strong": "台风(TY)",
      "power": 13,
      "move_dir": "北东北",
      "move_speed": 19.0
    },
    {
      "time": "2015-08-23T09:00:00",
      "lng": 123.410863,
      "lat": 23.303393,
      "pressure": 965,
      "speed": 38,
      "strong": "台风(TY)",
      "power": 13,
      "move_dir": "北东北",
      "move_speed": 19.0
    },
    {
      "time": "2015-08-23T10:00:00",
      "lng": 123.410852,
      "lat": 23.403412,
      "pressure": 965,
      "speed": 38,
      "strong": "台风(TY)",
      "power": 13,
      "move_dir": "北东北",
      "move_speed": 18.0
    },
    {
      "time": "2015-08-23T11:00:00",
      "lng": 123.410843,
      "lat": 23.50342,
      "pressure": 965,
      "speed": 38,
      "strong": "台风(TY)",
      "power": 13,
      "move_dir": "北东北",
      "move_speed": 20.0
    },
    {
      "time": "2015-08-23T12:00:00",
      "lng": 123.410853,
      "lat": 23.603418,
      "pressure": 965,
      "speed": 38,
      "strong": "台风(TY)",
      "power": 13,
      "move_dir": "东北",
      "move_speed": 21.0
    },
    {
      "time": "2015-08-23T13:00:00",
      "lng": 123.410878,
      "lat": 23.703407,
      "pressure": 965,
      "speed": 38,
      "strong": "台风(TY)",
      "power": 13,
      "move_dir": "东北",
      "move_speed": 21.0
    },
    {
      "time": "2015-08-23T14:00:00",
      "lng": 123.51066,
      "lat": 23.803564,
      "pressure": 960,
      "speed": 40,
      "strong": "台风(TY)",
      "power": 13,
      "move_dir": "东北",
      "move_speed": 23.0
    },
    {
      "time": "2015-08-23T15:00:00",
      "lng": 123.61043,
      "lat": 23.903596,
      "pressure": 960,
      "speed": 40,
      "strong": "台风(TY)",
      "power": 13,
      "move_dir": "东北",
      "move_speed": 23.0
    },
    {
      "time": "2015-08-23T16:00:00",
      "lng": 123.710598,
      "lat": 24.003583,
      "pressure": 960,
      "speed": 40,
      "strong": "台风(TY)",
      "power": 13,
      "move_dir": "东北",
      "move_speed": 23.0
    },
    {
      "time": "2015-08-23T17:00:00",
      "lng": 123.810661,
      "lat": 24.203138,
      "pressure": 945,
      "speed": 45,
      "strong": "强台风(STY)",
      "power": 14,
      "move_dir": "东北",
      "move_speed": 22.0
    },
    {
      "time": "2015-08-23T18:00:00",
      "lng": 123.910563,
      "lat": 24.302715,
      "pressure": 945,
      "speed": 45,
      "strong": "强台风(STY)",
      "power": 14,
      "move_dir": "东北",
      "move_speed": 27.0
    },
    {
      "time": "2015-08-23T19:00:00",
      "lng": 123.910586,
      "lat": 24.402691,
      "pressure": 940,
      "speed": 48,
      "strong": "强台风(STY)",
      "power": 15,
      "move_dir": "东北",
      "move_speed": 25.0
    },
    {
      "time": "2015-08-23T20:00:00",
      "lng": 124.010746,
      "lat": 24.50297,
      "pressure": 935,
      "speed": 52,
      "strong": "超强台风(Super TY)",
      "power": 16,
      "move_dir": "东北",
      "move_speed": 25.0
    },
    {
      "time": "2015-08-23T21:00:00",
      "lng": 124.110852,
      "lat": 24.503516,
      "pressure": 935,
      "speed": 52,
      "strong": "超强台风(Super TY)",
      "power": 16,
      "move_dir": "东北",
      "move_speed": 25.0
    },
    {
      "time": "2015-08-23T22:00:00",
      "lng": 124.210611,
      "lat": 24.603619,
      "pressure": 935,
      "speed": 52,
      "strong": "超强台风(Super TY)",
      "power": 16,
      "move_dir": "东北",
      "move_speed": 25.0
    },
    {
      "time": "2015-08-23T23:00:00",
      "lng": 124.310606,
      "lat": 24.703505,
      "pressure": 935,
      "speed": 52,
      "strong": "超强台风(Super TY)",
      "power": 16,
      "move_dir": "北东北",
      "move_speed": 30.0
    },
    {
      "time": "2015-08-24T00:00:00",
      "lng": 124.410832,
      "lat": 24.803295,
      "pressure": 935,
      "speed": 52,
      "strong": "超强台风(Super TY)",
      "power": 16,
      "move_dir": "北东北",
      "move_speed": 30.0
    },
    {
      "time": "2015-08-24T01:00:00",
      "lng": 124.510728,
      "lat": 25.002889,
      "pressure": 935,
      "speed": 52,
      "strong": "超强台风(Super TY)",
      "power": 16,
      "move_dir": "北东北",
      "move_speed": 30.0
    },
    {
      "time": "2015-08-24T02:00:00",
      "lng": 124.610505,
      "lat": 25.202836,
      "pressure": 930,
      "speed": 55,
      "strong": "超强台风(Super TY)",
      "power": 16,
      "move_dir": "北东北",
      "move_speed": 30.0
    },
    {
      "time": "2015-08-24T03:00:00",
      "lng": 124.810575,
      "lat": 25.303591,
      "pressure": 930,
      "speed": 55,
      "strong": "超强台风(Super TY)",
      "power": 16,
      "move_dir": "东北",
      "move_speed": 30.0
    },
    {
      "time": "2015-08-24T04:00:00",
      "lng": 125.010824,
      "lat": 25.50313,
      "pressure": 930,
      "speed": 55,
      "strong": "超强台风(Super TY)",
      "power": 16,
      "move_dir": "东北",
      "move_speed": 30.0
    },
    {
      "time": "2015-08-24T05:00:00",
      "lng": 125.210984,
      "lat": 25.602996,
      "pressure": 930,
      "speed": 55,
      "strong": "超强台风(Super TY)",
      "power": 16,
      "move_dir": "东北",
      "move_speed": 30.0
    },
    {
      "time": "2015-08-24T06:00:00",
      "lng": 125.310921,
      "lat": 25.803253,
      "pressure": 930,
      "speed": 55,
      "strong": "超强台风(Super TY)",
      "power": 16,
      "move_dir": "东北",
      "move_speed": 30.0
    },
    {
      "time": "2015-08-24T07:00:00",
      "lng": 125.710865,
      "lat": 26.002561,
      "pressure": 930,
      "speed": 55,
      "strong": "超强台风(Super TY)",
      "power": 16,
      "move_dir": "东北",
      "move_speed": 30.0
    },
    {
      "time": "2015-08-24T08:00:00",
      "lng": 125.810845,
      "lat": 26.202551,
      "pressure": 930,
      "speed": 55,
      "strong": "超强台风(Super TY)",
      "power": 16,
      "move_dir": "东北",
      "move_speed": 35.0
    },
    {
      "time": "2015-08-24T09:00:00",
      "lng": 126.010635,
      "lat": 26.503088,
      "pressure": 930,
      "speed": 55,
      "strong": "超强台风(Super TY)",
      "power": 16,
      "move_dir": "东北",
      "move_speed": 35.0
    },
    {
      "time": "2015-08-24T10:00:00",
      "lng": 126.310719,
      "lat": 26.702382,
      "pressure": 930,
      "speed": 55,
      "strong": "超强台风(Super TY)",
      "power": 16,
      "move_dir": "东北",
      "move_speed": 35.0
    },
    {
      "time": "2015-08-24T11:00:00",
      "lng": 126.510531,
      "lat": 27.00288,
      "pressure": 930,
      "speed": 55,
      "strong": "超强台风(Super TY)",
      "power": 16,
      "move_dir": "东北",
      "move_speed": 35.0
    },
    {
      "time": "2015-08-24T12:00:00",
      "lng": 126.81059,
      "lat": 27.302691,
      "pressure": 930,
      "speed": 55,
      "strong": "超强台风(Super TY)",
      "power": 16,
      "move_dir": "东北",
      "move_speed": 35.0
    },
    {
      "time": "2015-08-24T13:00:00",
      "lng": 127.110931,
      "lat": 27.603179,
      "pressure": 930,
      "speed": 55,
      "strong": "超强台风(Super TY)",
      "power": 16,
      "move_dir": "东北",
      "move_speed": 35.0
    },
    {
      "time": "2015-08-24T14:00:00",
      "lng": 127.411089,
      "lat": 27.802947,
      "pressure": 930,
      "speed": 55,
      "strong": "超强台风(Super TY)",
      "power": 16,
      "move_dir": "东北",
      "move_speed": 35.0
    },
    {
      "time": "2015-08-24T17:00:00",
      "lng": 128.010983,
      "lat": 28.702874,
      "pressure": 935,
      "speed": 52,
      "strong": "超强台风(Super TY)",
      "power": 16,
      "move_dir": "北东北",
      "move_speed": 35.0
    },
    {
      "time": "2015-08-24T20:00:00",
      "lng": 128.711191,
      "lat": 29.603177,
      "pressure": 935,
      "speed": 52,
      "strong": "超强台风(Super TY)",
      "power": 16,
      "move_dir": "北东北",
      "move_speed": 40.0
    },
    {
      "time": "2015-08-24T23:00:00",
      "lng": 129.511844,
      "lat": 30.503819,
      "pressure": 935,
      "speed": 52,
      "strong": "超强台风(Super TY)",
      "power": 16,
      "move_dir": "北东北",
      "move_speed": 39.0
    },
    {
      "time": "2015-08-25T02:00:00",
      "lng": 130.012083,
      "lat": 31.603926,
      "pressure": 940,
      "speed": 50,
      "strong": "强台风(STY)",
      "power": 15,
      "move_dir": "北东北",
      "move_speed": 28.0
    },
    {
      "time": "2015-08-25T05:00:00",
      "lng": 130.412349,
      "lat": 32.904419,
      "pressure": 945,
      "speed": 48,
      "strong": "强台风(STY)",
      "power": 15,
      "move_dir": "北东北",
      "move_speed": 25.0
    },
    {
      "time": "2015-08-25T08:00:00",
      "lng": 130.612042,
      "lat": 33.704314,
      "pressure": 950,
      "speed": 42,
      "strong": "强台风(STY)",
      "power": 14,
      "move_dir": "北东北",
      "move_speed": 24.0
    },
    {
      "time": "2015-08-25T11:00:00",
      "lng": 130.612112,
      "lat": 34.304486,
      "pressure": 955,
      "speed": 40,
      "strong": "台风(TY)",
      "power": 13,
      "move_dir": "北东北",
      "move_speed": 24.0
    },
    {
      "time": "2015-08-25T14:00:00",
      "lng": 130.812285,
      "lat": 35.106016,
      "pressure": 955,
      "speed": 40,
      "strong": "台风(TY)",
      "power": 13,
      "move_dir": "北东北",
      "move_speed": 24.0
    },
    {
      "time": "2015-08-25T17:00:00",
      "lng": 131.012648,
      "lat": 35.806153,
      "pressure": 965,
      "speed": 35,
      "strong": "台风(TY)",
      "power": 12,
      "move_dir": "北东北",
      "move_speed": 23.0
    },
    {
      "time": "2015-08-25T20:00:00",
      "lng": 131.212911,
      "lat": 36.406156,
      "pressure": 970,
      "speed": 33,
      "strong": "台风(TY)",
      "power": 12,
      "move_dir": "北东北",
      "move_speed": 26.0
    },
    {
      "time": "2015-08-25T23:00:00",
      "lng": 131.812775,
      "lat": 37.006454,
      "pressure": 975,
      "speed": 28,
      "strong": "强热带风暴(STS)",
      "power": 10,
      "move_dir": "北东北",
      "move_speed": 26.0
    },
    {
      "time": "2015-08-26T02:00:00",
      "lng": 131.912514,
      "lat": 37.906947,
      "pressure": 980,
      "speed": 25,
      "strong": "强热带风暴(STS)",
      "power": 10,
      "move_dir": "北",
      "move_speed": 21.0
    },
    {
      "time": "2015-08-26T05:00:00",
      "lng": 132.412944,
      "lat": 39.007129,
      "pressure": 980,
      "speed": 25,
      "strong": "强热带风暴(STS)",
      "power": 10,
      "move_dir": "北",
      "move_speed": 23.0
    },
    {
      "time": "2015-08-26T08:00:00",
      "lng": 132.812558,
      "lat": 39.207246,
      "pressure": 980,
      "speed": 25,
      "strong": "强热带风暴(STS)",
      "power": 10,
      "move_dir": "北西北",
      "move_speed": 25.0
    },
    {
      "time": "2015-08-26T11:00:00",
      "lng": 132.912574,
      "lat": 39.807015,
      "pressure": 980,
      "speed": 25,
      "strong": "强热带风暴(STS)",
      "power": 10,
      "move_dir": "北西北",
      "move_speed": 23.0
    },
    {
      "time": "2015-08-26T14:00:00",
      "lng": 133.012897,
      "lat": 40.307334,
      "pressure": 980,
      "speed": 25,
      "strong": "强热带风暴(STS)",
      "power": 10,
      "move_dir": "北西北",
      "move_speed": 25.0
    },
    {
      "time": "2015-08-26T17:00:00",
      "lng": 133.413264,
      "lat": 40.908117,
      "pressure": 980,
      "speed": 25,
      "strong": "强热带风暴(STS)",
      "power": 10,
      "move_dir": "北西北",
      "move_speed": 25.0
    },
    {
      "time": "2015-08-26T20:00:00",
      "lng": 133.213074,
      "lat": 41.808924,
      "pressure": 982,
      "speed": 23,
      "strong": "热带风暴(TS)",
      "power": 9,
      "move_dir": "北西北",
      "move_speed": 25.0
    },
    {
      "time": "2015-08-26T23:00:00",
      "lng": 132.91294,
      "lat": 42.207899,
      "pressure": 982,
      "speed": 23,
      "strong": "热带风暴(TS)",
      "power": 9,
      "move_dir": "西北",
      "move_speed": 24.0
    },
    {
      "time": "2015-08-27T02:00:00",
      "lng": 132.612743,
      "lat": 42.708689,
      "pressure": 982,
      "speed": 23,
      "strong": "热带风暴(TS)",
      "power": 9,
      "move_dir": "西西北",
      "move_speed": 22.0
    },
    {
      "time": "2015-08-27T05:00:00",
      "lng": 132.513225,
      "lat": 43.408739,
      "pressure": 986,
      "speed": 20,
      "strong": "热带风暴(TS)",
      "power": 8,
      "move_dir": "西北",
      "move_speed": 21.0
    },
    {
      "time": "2015-08-27T08:00:00",
      "lng": 131.013945,
      "lat": 44.308194,
      "pressure": 995,
      "speed": 18,
      "strong": "热带风暴(TS)",
      "power": 8,
      "move_dir": "西",
      "move_speed": 16.0
    }
  ]
}